molvoxel/__init__.py
molvoxel/config.py
molvoxel/etc/__init__.py
molvoxel/etc/pymol/__init__.py
molvoxel/etc/pymol/atom.py
molvoxel/etc/pymol/dx.py
molvoxel/etc/pymol/visualizer.py
molvoxel/etc/rdkit/__init__.py
molvoxel/etc/rdkit/base.py
molvoxel/etc/rdkit/getter.py
molvoxel/etc/rdkit/pointcloud.py
molvoxel/etc/rdkit/wrapper.py
molvoxel/voxelizer/__init__.py
molvoxel/voxelizer/base/__init__.py
molvoxel/voxelizer/base/transform.py
molvoxel/voxelizer/base/voxelizer.py
molvoxel/voxelizer/numba/__init__.py
molvoxel/voxelizer/numba/_quaternion.py
molvoxel/voxelizer/numba/func_features.py
molvoxel/voxelizer/numba/func_single.py
molvoxel/voxelizer/numba/func_types.py
molvoxel/voxelizer/numba/transform.py
molvoxel/voxelizer/numba/voxelizer.py
molvoxel/voxelizer/numpy/__init__.py
molvoxel/voxelizer/numpy/_quaternion.py
molvoxel/voxelizer/numpy/transform.py
molvoxel/voxelizer/numpy/voxelizer.py
molvoxel/voxelizer/torch/__init__.py
molvoxel/voxelizer/torch/_quaternion.py
molvoxel/voxelizer/torch/transform.py
molvoxel/voxelizer/torch/voxelizer.py
molvoxel-0.2.0.dist-info/licenses/LICENSE
molvoxel-0.2.0.dist-info/METADATA
molvoxel-0.2.0.dist-info/WHEEL
molvoxel-0.2.0.dist-info/top_level.txt
molvoxel-0.2.0.dist-info/RECORD
