Metadata-Version: 2.4
Name: molvoxel
Version: 0.2.0
Summary: MolVoxel:Easy-to-Use Molecular Voxelization Tool
Author-email: Seonghwan Seo <shwan0106@gmail.com>
Classifier: Intended Audience :: Developers
Classifier: Intended Audience :: Science/Research
Classifier: Development Status :: 4 - Beta
Classifier: Operating System :: OS Independent
Classifier: License :: OSI Approved :: MIT License
Classifier: Topic :: Scientific/Engineering
Classifier: Topic :: Scientific/Engineering :: Bio-Informatics
Classifier: Topic :: Scientific/Engineering :: Chemistry
Classifier: Topic :: Software Development :: Libraries :: Python Modules
Classifier: Programming Language :: Python :: 3.10
Classifier: Programming Language :: Python :: 3.11
Classifier: Programming Language :: Python :: 3.12
Classifier: Programming Language :: Python :: 3.13
Requires-Python: >=3.10
License-File: LICENSE
Requires-Dist: numpy
Requires-Dist: scipy
Provides-Extra: numba
Requires-Dist: numba; extra == "numba"
Provides-Extra: torch
Requires-Dist: torch; extra == "torch"
Provides-Extra: rdkit
Requires-Dist: rdkit; extra == "rdkit"
Dynamic: license-file
